advisor_utils/__init__.py
advisor_utils/candidate_generation.py
advisor_utils/cost_evaluation.py
advisor_utils/database_connector.py
advisor_utils/index.py
advisor_utils/postgres_dbms.py
advisor_utils/what_if_index_creation.py
advisor_utils/workload.py
index_advisor/__init__.py
index_advisor/drop_algorithm.py
index_advisor/extend_algorithm.py
index_advisor/selection_algorithm.py
bid_index_eab-0.1.0.dist-info/LICENSE
bid_index_eab-0.1.0.dist-info/METADATA
bid_index_eab-0.1.0.dist-info/WHEEL
bid_index_eab-0.1.0.dist-info/top_level.txt
bid_index_eab-0.1.0.dist-info/RECORD
